dj_db_conn_pool/__init__.py
dj_db_conn_pool/backends/__init__.py
dj_db_conn_pool/backends/jdbc/__init__.py
dj_db_conn_pool/backends/jdbc/utils.py
dj_db_conn_pool/backends/jdbc/oceanbase/__init__.py
dj_db_conn_pool/backends/jdbc/oceanbase/mixins.py
dj_db_conn_pool/backends/jdbc/oceanbase/mysql/__init__.py
dj_db_conn_pool/backends/jdbc/oceanbase/mysql/base.py
dj_db_conn_pool/backends/jdbc/oceanbase/oracle/__init__.py
dj_db_conn_pool/backends/jdbc/oceanbase/oracle/base.py
dj_db_conn_pool/backends/jdbc/oracle/__init__.py
dj_db_conn_pool/backends/jdbc/oracle/base.py
dj_db_conn_pool/backends/mysql/__init__.py
dj_db_conn_pool/backends/mysql/base.py
dj_db_conn_pool/backends/odbc/__init__.py
dj_db_conn_pool/backends/odbc/mixins.py
dj_db_conn_pool/backends/odbc/oceanbase/__init__.py
dj_db_conn_pool/backends/odbc/oceanbase/oracle/__init__.py
dj_db_conn_pool/backends/odbc/oceanbase/oracle/base.py
dj_db_conn_pool/backends/oracle/__init__.py
dj_db_conn_pool/backends/oracle/base.py
dj_db_conn_pool/backends/postgis/__init__.py
dj_db_conn_pool/backends/postgis/base.py
dj_db_conn_pool/backends/postgresql/__init__.py
dj_db_conn_pool/backends/postgresql/base.py
dj_db_conn_pool/backends/postgresql/mixins.py
dj_db_conn_pool/backends/postgresql/django_tenants/__init__.py
dj_db_conn_pool/backends/postgresql/django_tenants/base.py
dj_db_conn_pool/compat/__init__.py
dj_db_conn_pool/compat/jdbc.py
dj_db_conn_pool/core/__init__.py
dj_db_conn_pool/core/exceptions.py
dj_db_conn_pool/core/mixins/__init__.py
dj_db_conn_pool/core/mixins/core.py
dj_db_conn_pool/core/mixins/creation.py
django_database_connection_pool-0.0.1.dist-info/LICENSE
django_database_connection_pool-0.0.1.dist-info/METADATA
django_database_connection_pool-0.0.1.dist-info/WHEEL
django_database_connection_pool-0.0.1.dist-info/top_level.txt
django_database_connection_pool-0.0.1.dist-info/RECORD
