Metadata-Version: 2.1
Name: django-database-connection-pool
Version: 0.0.1
Summary: Database connection pool component library for Django
Author-email: Altair Bow <altair.bow@foxmail.com>
License: MIT License
Project-URL: homepage, https://github.com/daviddelucca/django-db-connection-pool
Project-URL: repository, https://github.com/daviddelucca/django-db-connection-pool
Keywords: django,db,database,persistent,connection,pool,pooling
Classifier: Development Status :: 5 - Production/Stable
Classifier: Environment :: Web Environment
Classifier: Framework :: Django
Classifier: Intended Audience :: Developers
Classifier: License :: OSI Approved :: MIT License
Classifier: Operating System :: OS Independent
Classifier: Programming Language :: Python :: 3
Classifier: Topic :: Software Development :: Libraries :: Python Modules
Requires-Python: >=3.4
License-File: LICENSE
Requires-Dist: Django >=2.0
Requires-Dist: SQLAlchemy >=1.4.24
Requires-Dist: sqlparams >=4.0.0
Provides-Extra: all
Requires-Dist: Django >=2.0 ; extra == 'all'
Requires-Dist: JPype1 >=1.3.0 ; extra == 'all'
Requires-Dist: SQLAlchemy >=1.4.24 ; extra == 'all'
Requires-Dist: cx-Oracle >=6.4.1 ; extra == 'all'
Requires-Dist: mysqlclient >=1.3.0 ; extra == 'all'
Requires-Dist: psycopg2 >=2.8.6 ; extra == 'all'
Requires-Dist: pyodbc >=4.0.34 ; extra == 'all'
Requires-Dist: sqlparams >=3.0.0 ; extra == 'all'
Provides-Extra: jdbc
Requires-Dist: JPype1 >=1.3.0 ; extra == 'jdbc'
Provides-Extra: mysql
Requires-Dist: mysqlclient >=1.3.0 ; extra == 'mysql'
Provides-Extra: odbc
Requires-Dist: pyodbc >=4.0.34 ; extra == 'odbc'
Provides-Extra: oracle
Requires-Dist: cx-Oracle >=6.4.1 ; extra == 'oracle'
Provides-Extra: postgresql
Requires-Dist: psycopg2 >=2.8.6 ; extra == 'postgresql'
Provides-Extra: psycopg2
Requires-Dist: psycopg2 >=2.8.6 ; extra == 'psycopg2'
Provides-Extra: psycopg3
Requires-Dist: psycopg >=3 ; extra == 'psycopg3'
